commoncodes/__init__.py
commoncodes/__main__.py
commoncodes/commoncodes.py
commoncodes-1.0.3.dist-info/METADATA
commoncodes-1.0.3.dist-info/WHEEL
commoncodes-1.0.3.dist-info/top_level.txt
commoncodes-1.0.3.dist-info/RECORD
