Metadata-Version: 2.1
Name: commoncodes
Version: 1.0.3
Summary: Uses the commoncodes standard to create more specific Exceptions
Home-page: https://github.com/RiedleroD/commoncodes.py
Author: Riedler
Author-email: dev@riedler.wien
License: Creative Commons BY-SA 4.0
Platform: UNKNOWN
Classifier: Programming Language :: Python :: 3
Classifier: Programming Language :: Python :: 3.8
